{"name": "trip-bolzano-esn-trento", "description": "Needed to activate contextual links class group-image class colorbox data-cbox-img-attrs '{title: , alt: }' data-colorbox-gallery gallery-node-30950-pi6Tru03II8 href oTe4WuKx title img alt src 7MJbcPO4 title //a class group-content class o9v6fnle cxmmr5t8 oygrvhab hcukyx3x c1et5uqlAre you ready for the first day-trip of your Erasmus? Let's start the Welcome Week with the right foot by discovering another beautiful city in the Trentino region! class o9v6fnle cxmmr5t8 oygrvhab hcukyx3x c1et5uqlWe will meet with our friends from ESN Bolzano and discover the city with them. class o9v6fnle cxmmr5t8 oygrvhab hcukyx3x c1et5uqlThe train ticket is on behalf of the participants, no other fee! We will meet at the train station at 13:00 and catch the train at 13:30.br/ As soon as we arrive, ESN Bolzano will show us around the town. Afterwards, we'll have a snack/drink all together and be back in Trento before the evening .br/ NB: the event will be postponed in case of bad weather, we will keep you informed class group-secondary class date-display-single16/02/2020 - 13:00 class countryItaly", "location": "Italy bolzano Bolzano ESN and Bolzano ESN will Trento in before", "duration_hours": [" 13:00 "], "duration_days": ["16/02/2020 "], "links": ["https://trento.esn.it/sites/esntrento.it/files/styles/zoom/public/events/images/trip_to_bozen_2020.jpg?itok", "https://trento.esn.it/sites/esntrento.it/files/styles/page/public/events/images/trip_to_bozen_2020.jpg?itok"], "schema": [], "info": [], "recurrency": ["16/02/2020 "], "lat_lon": [34.11631798800005, 9.60851649600005], "is_online": false, "is_offline": true, "is_blended": false, "ticket": ["ticket", "is", "on", "behalf", "of", "the", "participants,", "no", "other", "fee!", "We", "will", "meet", "at", "the", "train", "station", "at", "13:00", "and", "catch", "the", "train", "at", "13:30.br/", "As", "soon", "as", "we", "arrive,", "ESN", "Bolzano", "will", "show", "us", "around", "the", "town.", "Afterwards,", "we'll", "have", "a", "snack/drink", "all", "together", "and", "be", "back", "in", "Trento", "before", "the", "evening", ".br/", "NB:", "the", "event", "will", "be", "postponed", "in", "case", "of", "bad", "weather,", "we", "will", "keep", "you", "informed", "class", "group-secondary", "class", "date-display-single16/02/2020", "-", "13:00", "class", "countryItaly"], "category": "trip"}